ackuq/pit/__init__.py
ackuq/pit/context.py
spark_pit-0.5.0.dist-info/METADATA
spark_pit-0.5.0.dist-info/WHEEL
spark_pit-0.5.0.dist-info/top_level.txt
spark_pit-0.5.0.dist-info/RECORD
